adafruit_ble_beacon.py
adafruit_circuitpython_ble_beacon-1.0.11.dist-info/licenses/LICENSE
adafruit_circuitpython_ble_beacon-1.0.11.dist-info/METADATA
adafruit_circuitpython_ble_beacon-1.0.11.dist-info/WHEEL
adafruit_circuitpython_ble_beacon-1.0.11.dist-info/top_level.txt
adafruit_circuitpython_ble_beacon-1.0.11.dist-info/RECORD
